giffer/__init__.py
giffer/src/__init__.py
giffer/src/_pyplot_extension.py
giffer/src/_temp.py
giffer/src/_util.py
giffer/src/tests/__init__.py
giffer/src/tests/test_gif_obj.py
giffer/src/tests/test_making_gif.py
giffer-0.1.2.dist-info/LICENSE
giffer-0.1.2.dist-info/METADATA
giffer-0.1.2.dist-info/WHEEL
giffer-0.1.2.dist-info/top_level.txt
giffer-0.1.2.dist-info/RECORD
