Metadata-Version: 2.1
Name: giffer
Version: 0.1.2
Summary: Basic .gif converter
Home-page: https://github.com/salomaestro/giffer
Author: Salomaestro
Author-email: <chris10an.salomonsen@gmail.com>
License: UNKNOWN
Keywords: python,basic,gif
Platform: UNKNOWN
Classifier: Operating System :: Microsoft :: Windows
Classifier: Operating System :: MacOS :: MacOS X
License-File: LICENSE
Requires-Dist: imageio
Requires-Dist: numpy
Requires-Dist: Pillow
